handlerConsoleCRUD/Funciones.py
handlerConsoleCRUD/__init__.py
handlerConsoleCRUD-0.0.5.dist-info/METADATA
handlerConsoleCRUD-0.0.5.dist-info/WHEEL
handlerConsoleCRUD-0.0.5.dist-info/top_level.txt
handlerConsoleCRUD-0.0.5.dist-info/RECORD
