Metadata-Version: 2.1
Name: handlerConsoleCRUD
Version: 0.0.5
Summary: Librería QUE TE PERMITE DEFINIR LOS CAMPOS DE TU CRUD 
Home-page: https://github.com/EstCarlos
Author: Carlos Soto De Dios
Author-email: 1106419@est.intec.edu.do
License: MIT
